def_main.py
def_main-0.11.0.dist-info/WHEEL
def_main-0.11.0.dist-info/METADATA
def_main-0.11.0.dist-info/RECORD
