Metadata-Version: 2.1
Name: def-main
Version: 0.11.0
Summary: Define the main function in one step and make it testable
License: MIT
Author: Tom Ritchford
Author-email: tom@swirly.com
Requires-Python: >=3.7,<4.0
Classifier: License :: OSI Approved :: MIT License
Classifier: Programming Language :: Python :: 3
Classifier: Programming Language :: Python :: 3.7
Classifier: Programming Language :: Python :: 3.8
Classifier: Programming Language :: Python :: 3.9
Classifier: Programming Language :: Python :: 3.10
Classifier: Programming Language :: Python :: 3.11
